Workbook

Sheet Executive Summary
A1: Pakistan Economic & Debt Review (2013–2025) — Executive Summary
A2: One-page print summary | B2: Built from the workbook’s Yearly Macro, Tenure, Loan Program, Debt Servicing, and Provincial sheets. Intended for executive comparison and briefing.
A4: Best average growth | C4: Largest debt increase | E4: Recent stabilization winner | G4: Public debt FY2024-25 (PKR bn)
A5: ='Political Dashboard'!E6 | C5: ='Political Dashboard'!E8 | E5: "Shehbaz Sharif" | G5: ='Yearly Macro'!E13
A8: Metric | B8: Nawaz / PML-N | C8: Imran Khan | D8: Shehbaz Sharif | E8: Verdict | G8: Color-coded verdicts
A9: Average GDP Growth (%) | B9: ='Political Dashboard'!B6 | C9: ='Political Dashboard'!C6 | D9: ='Political Dashboard'!D6 | E9: Best: Nawaz | G9: Green | H9: Strongest score on the metric
A10: Average Inflation (%) | B10: ='Political Dashboard'!B7 | C10: ='Political Dashboard'!C7 | D10: ='Political Dashboard'!D7 | E10: Lowest is better | G10: Yellow | H10: Mixed / stabilization / context needed
A11: Debt Increase (PKR bn) | B11: ='Political Dashboard'!B8 | C11: ='Political Dashboard'!C8 | D11: ='Political Dashboard'!D8 | E11: Highest: Shehbaz | G11: Red | H11: Weakest or most concerning score on the metric
A12: Start Debt/GDP (%) | B12: ='Political Dashboard'!B9 | C12: ='Political Dashboard'!C9 | D12: ='Political Dashboard'!D9 | E12: Context only
A13: End Debt/GDP (%) | B13: ='Political Dashboard'!B10 | C13: ='Political Dashboard'!C10 | D13: ='Political Dashboard'!D10 | E13: Context only | G13: Executive takeaways
G14: • | H14: Nawaz era had the strongest average growth in the series.
A15: Source note | B15: See Yearly Macro, Major Loan Programs, External Flows, Debt Servicing, Provincial Debt, and Political Dashboard sheets for source URLs and detailed assumptions.
G16: • | H16: Shehbaz era was dominated by stabilization; debt still rose sharply.
G17: • | H17: Pakistan’s debt problem is structural: deficit financing, servicing, rollover, and FX effects.

Sheet Lender Heatmap
A1: Lender Heatmap (selected official disbursement snapshots, USD mn)
A2: Caveat: this heatmap uses the best official snapshots surfaced in the workbook/web research. Some years have partial lender detail (especially China/WB/ADB in FY2021-22 and FY2024-25). Blank cells mean detail was not surfaced cleanly in the current source set, not necessarily zero.
A3: FY snapshot | B3: IMF | C3: World Bank | D3: ADB | E3: China | F3: Gulf | G3: Commercial | H3: Bonds / Sukuk | I3: Source URL
A4: FY2016-17 | B4: 102 | C4: 904 | D4: 1495 | E4: 3955 | F4: 514 | G4: 4370 | H4: 1000 | I4: https://www.finance.gov.pk/publications/DPS_2017_18.pdf
A5: FY2021-22 | B5: 1053 | F5: 3000 | G5: 2623 | H5: 2000 | I5: https://www.finance.gov.pk/survey/chapter_22/Economic%20Survey_2021-22.pdf
A6: FY2022-23 | B6: 1166 | C6: 1218 | D6: 1939 | F6: 883 | G6: 900 | H6: 0 | I6: https://www.finance.gov.pk/survey/chapters_23/Economic_Survey_2022_23.pdf
A7: FY2023-24 | B7: 1200 | C7: 2200 | D7: 1300 | F7: 2000 | I7: https://www.finance.gov.pk/dpco/Annual_Debt_Review_FY24.pdf
A8: FY2024-25 | B8: 1000 | F8: 500 | G8: 1000 | H8: 0 | I8: https://www.finance.gov.pk/mefp/extended_Fund_Facility_October_2024.pdf
A10: Average disclosed flow | B10: =AVERAGE(B4:B8) | C10: =AVERAGE(C4:C8) | D10: =AVERAGE(D4:D8) | E10: =AVERAGE(E4:E8) | F10: =AVERAGE(F4:F8) | G10: =AVERAGE(G4:G8) | H10: =AVERAGE(H4:H8)

Sheet Debt Sustainability
A1: Debt Sustainability Model (simplified projection)
A2: This is a simplified analyst model, not an IMF DSA. Yellow cells are assumptions you can change. Formulas project debt, GDP, debt/GDP, and interest/revenue under different assumptions.
A4: Input | B4: Value
A5: Base Debt (PKR bn) | B5: 80518
A6: Base GDP (PKR bn) | B6: 114692
A7: External debt share (%) | B7: 0.325
A8: Base interest expense (PKR bn) | B8: 8887
A9: Revenue-to-GDP assumption (%) | B9: 0.15
A10: Nominal GDP growth assumption (%) | B10: 0.1
A11: Average effective interest rate on debt (%) | B11: 0.11
A12: Primary balance assumption (% GDP, surplus positive) | B12: 0.01
A13: Annual FX depreciation shock (%) | B13: 0
A14: Oil shock add-on financing need (% GDP) | B14: 0
A18: FY | B18: Opening Debt (PKR bn) | C18: GDP (PKR bn) | D18: Interest Expense (PKR bn) | E18: Primary Balance (PKR bn) | F18: FX Shock (PKR bn) | G18: Oil Shock Need (PKR bn) | H18: Closing Debt (PKR bn) | I18: Debt/GDP (%) | J18: Revenue (PKR bn) | K18: Interest/Revenue (%)
A19: FY2025-26 | B19: =B5 | C19: =B6*(1+$B$10) | D19: =B19*$B$11 | E19: =C19*$B$12 | F19: =B19*$B$7*$B$13 | G19: =C19*$B$14 | H19: =B19+D19-E19+F19+G19 | I19: =H19/C19 | J19: =C19*$B$9 | K19: =D19/J19
A20: FY2026-27 | B20: =H19 | C20: =C19*(1+$B$10) | D20: =B20*$B$11 | E20: =C20*$B$12 | F20: =B20*$B$7*$B$13 | G20: =C20*$B$14 | H20: =B20+D20-E20+F20+G20 | I20: =H20/C20 | J20: =C20*$B$9 | K20: =D20/J20
A21: FY2027-28 | B21: =H20 | C21: =C20*(1+$B$10) | D21: =B21*$B$11 | E21: =C21*$B$12 | F21: =B21*$B$7*$B$13 | G21: =C21*$B$14 | H21: =B21+D21-E21+F21+G21 | I21: =H21/C21 | J21: =C21*$B$9 | K21: =D21/J21
A22: FY2028-29 | B22: =H21 | C22: =C21*(1+$B$10) | D22: =B22*$B$11 | E22: =C22*$B$12 | F22: =B22*$B$7*$B$13 | G22: =C22*$B$14 | H22: =B22+D22-E22+F22+G22 | I22: =H22/C22 | J22: =C22*$B$9 | K22: =D22/J22
A23: FY2029-30 | B23: =H22 | C23: =C22*(1+$B$10) | D23: =B23*$B$11 | E23: =C23*$B$12 | F23: =B23*$B$7*$B$13 | G23: =C23*$B$14 | H23: =B23+D23-E23+F23+G23 | I23: =H23/C23 | J23: =C23*$B$9 | K23: =D23/J23

Sheet Scenario Simulator
A1: Scenario Simulator
A2: Change the scenario assumptions in columns B:E. Formulas show the immediate model impact relative to the FY2025 base. This is a simplified stress-testing tool.
A3: Variable | B3: Base | C3: PKR devaluation +10% | D3: Oil shock | E3: Combined shock | F3: Units | G3: Definition | H3: Source / note
A4: GDP growth shock | B4: 0 | C4: 0 | D4: -0.01 | E4: -0.01 | F4: % | G4: Reduction in nominal GDP growth vs base | H4: Analyst assumption
A5: FX depreciation shock | B5: 0 | C5: 0.1 | D5: 0 | E5: 0.1 | F5: % | G5: Applied to external debt share only | H5: Analyst assumption
A6: Oil shock financing need | B6: 0 | C6: 0 | D6: 0.005 | E6: 0.005 | F6: % GDP | G6: Additional financing need from costlier oil / subsidies / imports | H6: Analyst assumption
A7: Interest rate shock | B7: 0 | C7: 0 | D7: 0.01 | E7: 0.01 | F7: % | G7: Increase in effective interest rate | H7: Analyst assumption
A10: Outcome metric | B10: Base | C10: PKR devaluation +10% | D10: Oil shock | E10: Combined shock | F10: Formula logic
A11: Debt add-on from FX shock (PKR bn) | B11: ='Debt Sustainability'!B5*'Debt Sustainability'!B7*B5 | C11: ='Debt Sustainability'!B5*'Debt Sustainability'!B7*C5 | D11: ='Debt Sustainability'!B5*'Debt Sustainability'!B7*D5 | E11: ='Debt Sustainability'!B5*'Debt Sustainability'!B7*E5 | F11: Debt * external share * FX shock
A12: Oil-shock financing need (PKR bn) | B12: ='Debt Sustainability'!B6*B6 | C12: ='Debt Sustainability'!B6*C6 | D12: ='Debt Sustainability'!B6*D6 | E12: ='Debt Sustainability'!B6*E6 | F12: GDP * extra financing need
A13: Interest expense after rate shock (PKR bn) | B13: ='Debt Sustainability'!B8*(1+B7) | C13: ='Debt Sustainability'!B8*(1+C7) | D13: ='Debt Sustainability'!B8*(1+D7) | E13: ='Debt Sustainability'!B8*(1+E7) | F13: Base interest * (1 + shock)
A14: Approx. stressed debt stock (PKR bn) | B14: =B11+B12+'Debt Sustainability'!B5 | C14: =C11+C12+'Debt Sustainability'!B5 | D14: =D11+D12+'Debt Sustainability'!B5 | E14: =E11+E12+'Debt Sustainability'!B5 | F14: Base debt + FX add-on + oil financing
A15: Approx. stressed debt/GDP (%) | B15: =(B14)/('Debt Sustainability'!B6*(1+'Debt Sustainability'!B10+B4)) | C15: =(C14)/('Debt Sustainability'!B6*(1+'Debt Sustainability'!B10+C4)) | D15: =(D14)/('Debt Sustainability'!B6*(1+'Debt Sustainability'!B10+D4)) | E15: =(E14)/('Debt Sustainability'!B6*(1+'Debt Sustainability'!B10+E4)) | F15: Stressed debt / stressed GDP

Sheet Power Sector
A1: Power Sector Deep Dive / Circular Debt Tracking
A2: Tracks a few headline circular-debt markers surfaced in official budget / finance / news sources. It is not a full electricity-sector financial model.
A3: Year / marker | B3: Circular debt (PKR bn) | C3: Change vs prior marker | D3: Event / note | E3: Political context | F3: Source URL
A4: 2018 | B4: 1148 | D4: Budget speech says circular debt had increased to Rs 1,148 bn by 2018. | E4: End of PML-N era marker | F4: https://www.finance.gov.pk/budget/Budget_2023_24/Speech_english_2023_24.pdf
A5: 2022 | B5: 2467 | C5: =B5-B4 | D5: In 4 PTI years it increased by Rs 1,319 bn to Rs 2,467 bn. | E5: PTI-era end marker | F5: https://www.finance.gov.pk/budget/Budget_2023_24/Speech_english_2023_24.pdf
A6: 2024 | D6: Energy-sector reform remained a priority in IMF-linked stabilization. | E6: Post-crisis stabilization period | F6: https://www.finance.gov.pk/pr_oct_dec_2022.html
A7: 2025 bank facility | B7: 1275 | D7: Islamic finance facility with 18 local banks signed to ease power-sector debt burden. | E7: Current restructuring step | F7: https://www.reuters.com/sustainability/boards-policy-regulation/pakistan-signs-45-billion-loans-with-local-banks-ease-power-sector-debt-2025-06-20/

Sheet Election Analysis
A1: Election-Year Analysis / Spending vs Growth Patterns
A2: Election linkage is simplified: FY2013-14, FY2017-18, FY2018-19, and FY2023-24 are flagged as election-linked or transition-adjacent fiscal years for pattern reading. Spending-side precision would improve further with direct budget-book extraction.
A3: Fiscal Year | B3: Election-linked? | C3: Tenure | D3: GDP Growth (%) | E3: Public Debt (PKR bn) | F3: YoY Debt Growth (%) | G3: Comment | H3: Source URL | J3: Pattern summary | K3: Value
A4: FY2013-14 | B4: Yes | C4: ='Yearly Macro'!B2 | D4: ='Yearly Macro'!C2 | E4: ='Yearly Macro'!E2 | G4: Election / transition-adjacent year; compare growth with debt build-up. | H4: ='Yearly Macro'!I2 | J4: Avg GDP growth in election-linked FYs | K4: =AVERAGEIF(B4:B15,"Yes",D4:D15)
A5: FY2014-15 | B5: No | C5: ='Yearly Macro'!B3 | D5: ='Yearly Macro'!C3 | E5: ='Yearly Macro'!E3 | F5: =(E5/E4)-1 | H5: ='Yearly Macro'!I3 | J5: Avg GDP growth in non-election FYs | K5: =AVERAGEIF(B4:B15,"No",D4:D15)
A6: FY2015-16 | B6: No | C6: ='Yearly Macro'!B4 | D6: ='Yearly Macro'!C4 | E6: ='Yearly Macro'!E4 | F6: =(E6/E5)-1 | H6: ='Yearly Macro'!I4 | J6: Avg debt growth in election-linked FYs | K6: =AVERAGEIF(B4:B15,"Yes",F4:F15)
A7: FY2016-17 | B7: No | C7: ='Yearly Macro'!B5 | D7: ='Yearly Macro'!C5 | E7: ='Yearly Macro'!E5 | F7: =(E7/E6)-1 | H7: ='Yearly Macro'!I5 | J7: Avg debt growth in non-election FYs | K7: =AVERAGEIF(B4:B15,"No",F4:F15)
A8: FY2017-18 | B8: Yes | C8: ='Yearly Macro'!B6 | D8: ='Yearly Macro'!C6 | E8: ='Yearly Macro'!E6 | F8: =(E8/E7)-1 | G8: Election / transition-adjacent year; compare growth with debt build-up. | H8: ='Yearly Macro'!I6
A9: FY2018-19 | B9: Yes | C9: ='Yearly Macro'!B7 | D9: ='Yearly Macro'!C7 | E9: ='Yearly Macro'!E7 | F9: =(E9/E8)-1 | G9: Election / transition-adjacent year; compare growth with debt build-up. | H9: ='Yearly Macro'!I7
A10: FY2019-20 | B10: No | C10: ='Yearly Macro'!B8 | D10: ='Yearly Macro'!C8 | E10: ='Yearly Macro'!E8 | F10: =(E10/E9)-1 | H10: ='Yearly Macro'!I8
A11: FY2020-21 | B11: No | C11: ='Yearly Macro'!B9 | D11: ='Yearly Macro'!C9 | E11: ='Yearly Macro'!E9 | F11: =(E11/E10)-1 | H11: ='Yearly Macro'!I9
A12: FY2021-22 | B12: No | C12: ='Yearly Macro'!B10 | D12: ='Yearly Macro'!C10 | E12: ='Yearly Macro'!E10 | F12: =(E12/E11)-1 | H12: ='Yearly Macro'!I10
A13: FY2022-23 | B13: No | C13: ='Yearly Macro'!B11 | D13: ='Yearly Macro'!C11 | E13: ='Yearly Macro'!E11 | F13: =(E13/E12)-1 | H13: ='Yearly Macro'!I11
A14: FY2023-24 | B14: Yes | C14: ='Yearly Macro'!B12 | D14: ='Yearly Macro'!C12 | E14: ='Yearly Macro'!E12 | F14: =(E14/E13)-1 | G14: Election / transition-adjacent year; compare growth with debt build-up. | H14: ='Yearly Macro'!I12
A15: FY2024-25 | B15: No | C15: ='Yearly Macro'!B13 | D15: ='Yearly Macro'!C13 | E15: ='Yearly Macro'!E13 | F15: =(E15/E14)-1 | H15: ='Yearly Macro'!I13

Sheet Provincial Trends
A1: Province-wise debt indicators (Punjab vs Sindh)
A2: Punjab trend uses official debt stock snapshots. Sindh trend mixes total debt liability (2021), external public debt proxy (2023), and FY2024-25 debt increase/servicing where a clean total stock was not surfaced in the current source set. Use as a directional chart, not a statutory series.
A3: Year | B3: Punjab metric type | C3: Punjab value | D3: Sindh metric type | E3: Sindh value | F3: Comparable? | G3: Punjab source | H3: Sindh source
A4: 2020 | B4: Punjab debt stock (PKR bn) | C4: 945.5 | D4: - | E4: - | F4: No | G4: https://finance.punjab.gov.pk/system/files/FRS21-22.pdf
A5: 2021 | B5: Punjab debt stock (PKR bn) | C5: 955 | D5: Sindh total debt liability (PKR bn) | E5: 603.6 | F5: Partial | G5: https://finance.punjab.gov.pk/system/files/FRS22-23.pdf | H5: https://finance.gos.pk/Latest/downloadNotification?path=Notifications%2FUpdate%2F45334e9a-5f3c-4474-a368-d6f4d1eb7e53-Budget+Strategy+paper+2022-25.pdf
A6: 2022 | B6: Punjab debt stock (approx PKR bn) | C6: 1131 | D6: - | E6: - | F6: No | G6: https://finance.punjab.gov.pk/system/files/Debt%20Bulletin%20June-2022.pdf
A7: 2023 | B7: Punjab external public debt (USD mn) | C7: 5951 | D7: Sindh external public debt (USD mn) | E7: 3125 | F7: Yes (USD proxy) | G7: https://www.finance.gov.pk/publications/Annual_Debt_Review_FY_2022_23.pdf | H7: https://www.finance.gov.pk/publications/Annual_Debt_Review_FY_2022_23.pdf
A8: 2024 | B8: Punjab debt stock (PKR bn) | C8: 1677 | D8: Sindh debt servicing FY24-25 (PKR bn) | E8: 71.38 | F8: No | G8: https://finance.punjab.gov.pk/system/files/DebtBulletinJun24.pdf | H8: https://finance.gos.pk/Home/Download?path=SpecializedUnits%2FDMU%2FDEBT+BULLETIN+30-06-25.pdf
A9: 2025 | B9: Punjab debt stock (PKR bn) | C9: 1757.2 | D9: Sindh FY24-25 debt increase (PKR bn) | E9: 284.951 | F9: No | G9: https://finance.punjab.gov.pk/system/files/punjab_debt_bulletin_june_2025.pdf | H9: https://finance.gos.pk/Home/Download?path=SpecializedUnits%2FDMU%2FDEBT+BULLETIN+30-06-25.pdf

Sheet PM Scorecards
A1: Prime Minister Scorecards
A3: Nawaz / PML-N Scorecard | F3: Imran Khan Scorecard | K3: Shehbaz Sharif Scorecard
A4: Average GDP Growth (%) | C4: =Nawaz!K5 | F4: Average GDP Growth (%) | H4: =Imran!K5 | K4: Average GDP Growth (%) | M4: =Shehbaz!K5
A5: Average Inflation (%) | C5: =Nawaz!K6 | F5: Average Inflation (%) | H5: =Imran!K6 | K5: Average Inflation (%) | M5: =Shehbaz!K6
A6: Debt Increase (PKR bn) | C6: =Nawaz!K7 | F6: Debt Increase (PKR bn) | H6: =Imran!K7 | K6: Debt Increase (PKR bn) | M6: =Shehbaz!K7
A7: Start Debt/GDP (%) | C7: =Nawaz!K8 | F7: Start Debt/GDP (%) | H7: =Imran!K8 | K7: Start Debt/GDP (%) | M7: =Shehbaz!K8
A8: End Debt/GDP (%) | C8: =Nawaz!K9 | F8: End Debt/GDP (%) | H8: =Imran!K9 | K8: End Debt/GDP (%) | M8: =Shehbaz!K9
A9: Years covered | C9: =Nawaz!K10 | F9: Years covered | H9: =Imran!K10 | K9: Years covered | M9: =Shehbaz!K10
A10: Scorecard comment | F10: Scorecard comment | K10: Scorecard comment
A11: Growth leader in this comparison. Macro expansion was stronger, but vulnerabilities accumulated by the end of the period. | F11: Volatile period. Growth was hit by stabilization and COVID, then rebounded sharply, but debt and external stress worsened. | K11: Stabilization-focused period. Inflation cooled and the macro picture improved by FY2025, but debt kept rising.
A16: Metric | B16: Nawaz | C16: Imran | D16: Shehbaz | F16: Verdict legend
A17: Average GDP Growth (%) | B17: =Nawaz!K5 | C17: =Imran!K5 | D17: =Shehbaz!K5 | F17: Green | G17: Best comparative score
A18: Debt Increase (PKR bn) | B18: =Nawaz!K7 | C18: =Imran!K7 | D18: =Shehbaz!K7 | F18: Yellow | G18: Mixed / context-heavy
A19: End Debt/GDP (%) | B19: =Nawaz!K9 | C19: =Imran!K9 | D19: =Shehbaz!K9 | F19: Red | G19: Weakest / risk-heavy
A22: Source note | B22: All scorecards link to the Nawaz, Imran, and Shehbaz sheets, which in turn link to Yearly Macro.

Sheet Political Dashboard
A1: Pakistan Political Comparison Dashboard (V2)
A2: Dashboard note | B2: Built from the Yearly Macro sheet and tenure sheets. Use this for quick political comparisons, not as a substitute for primary source documents.
A5: Metric | B5: Nawaz / PML-N | C5: Imran Khan | D5: Shehbaz Sharif | E5: Best / Highest | G5: Political verdict scorecard
A6: Average GDP Growth (%) | B6: =Nawaz!K5 | C6: =Imran!K5 | D6: =Shehbaz!K5 | E6: =INDEX(B6:D6,MATCH(MAX(B6:D6),B6:D6,0)) | G6: Fastest average growth | H6: =E6
A7: Average Inflation (%) | B7: =Nawaz!K6 | C7: =Imran!K6 | D7: =Shehbaz!K6 | E7: "Lower is better" | G7: Largest debt increase | H7: =E8
A8: Debt Increase (PKR bn) | B8: =Nawaz!K7 | C8: =Imran!K7 | D8: =Shehbaz!K7 | E8: =INDEX(B8:D8,MATCH(MAX(B8:D8),B8:D8,0)) | G8: Most recent stabilization winner | H8: "Shehbaz Sharif (FY2024-25 macro stabilization)"
A9: Start Debt/GDP (%) | B9: =Nawaz!K8 | C9: =Imran!K8 | D9: =Shehbaz!K8 | E9: "-"
A10: End Debt/GDP (%) | B10: =Nawaz!K9 | C10: =Imran!K9 | D10: =Shehbaz!K9 | E10: "-" | G10: Interpretation cautions
A11: Years Covered | B11: =Nawaz!K10 | C11: =Imran!K10 | D11: =Shehbaz!K10 | E11: =SUM(B11:D11) | G11: • | H11: Debt jumps in later years were amplified by rupee depreciation.
G12: • | H12: FY2021-22 is assigned to Imran for comparability, though it was a transition year.
G13: • | H13: Growth quality and stabilization are not the same thing.
A29: Sources | B29: See Yearly Macro, Major Loan Programs, External Flows, Debt Servicing, and Provincial Debt sheets for plain-text URLs and notes.

Sheet README
A1: Pakistan Economic Statistics & Loan Breakdown (2013–2025)
A3: What this workbook includes
A4: 1) Yearly macro table by fiscal year (growth, inflation, debt)
A5: 2) Major loan programs and facilities (IMF + notable financing)
A6: 3) External inflows / repayments breakdown from official debt statements
A7: 4) Debt servicing sheet
A8: 5) Tenure summary with formulas
A9: 6) Provincial debt snapshot
A11: Important caveat
A12: Use this workbook as an analyst briefing file, not as a legal/statutory publication. Some annual debt rows are compiled from multiple official debt reviews/summaries for continuity. Validate against the latest SBP annual debt summary before public release.

Sheet Yearly Macro
A1: Fiscal Year | B1: Tenure | C1: Real GDP Growth (%) | D1: Inflation (%) | E1: Public Debt (PKR bn) | F1: Debt/GDP (%) | G1: Current Account (USD bn) | H1: Data note | I1: Source URL
A2: FY2013-14 | B2: Nawaz / PML-N | C2: 4.03 | D2: 8.6 | E2: 14366 | F2: 62.7 | H2: Growth & inflation from official year books/surveys; debt from MoF debt statement surfaced in official debt docs. | I2: https://www.finance.gov.pk/publications/YearBook2013_14.pdf
A3: FY2014-15 | B3: Nawaz / PML-N | C3: 4.24 | D3: 4.53 | E3: 15992 | F3: 63.5 | G3: -1.4 | H3: Current-account figure shown for Jul-Apr in survey highlights; use with care. | I3: https://www.finance.gov.pk/publications/YearBook2014_15.pdf
A4: FY2015-16 | B4: Nawaz / PML-N | C4: 4.71 | D4: 2.9 | E4: 17381 | F4: 63.3 | H4: Debt row compiled to maintain annual continuity; validate vs SBP summary for publication. | I4: https://www.finance.gov.pk/survey/chapters_16/highlights_2015_16.pdf
A5: FY2016-17 | B5: Nawaz / PML-N | C5: 5.28 | D5: 4.8 | E5: 21407 | F5: 67.2 | H5: Official debt stock and GDP ratio from Debt Policy Statement 2017-18. | I5: https://www.finance.gov.pk/publications/DPS_2017_18.pdf
A6: FY2017-18 | B6: Nawaz / PML-N | C6: 5.8 | D6: 4.7 | E6: 24953 | F6: 72.5 | H6: Debt ratio from DPS 2018-19; debt stock compiled for annual continuity. | I6: https://www.finance.gov.pk/publications/DPS_2018_19.pdf
A7: FY2018-19 | B7: Imran Khan | C7: 2.08 | D7: 6.8 | E7: 32708 | F7: 74.7 | H7: Debt stock compiled; debt ratio from official DPS 2019-20 context. | I7: https://www.finance.gov.pk/publications/DPS_2019_2020.pdf
A8: FY2019-20 | B8: Imran Khan | C8: -0.47 | D8: 10.7 | E8: 36399 | F8: 76.6 | H8: COVID year; growth from Economic Survey 2020-21 back-series. | I8: https://www.finance.gov.pk/survey/chapters_21/01-Growth.pdf
A9: FY2020-21 | B9: Imran Khan | C9: 3.94 | D9: 8.9 | E9: 39866 | F9: 71.5 | H9: Growth from Economic Survey 2020-21; debt series compiled from debt reviews. | I9: https://www.finance.gov.pk/survey/chapters_21/01-Growth.pdf
A10: FY2021-22 | B10: Imran Khan | C10: 5.97 | D10: 12.2 | E10: 49242 | F10: 73.9 | H10: Official debt row surfaced in Debt Policy Statement January 2024 / 2023 review. | I10: https://www.finance.gov.pk/publications/DPS_2023.pdf
A11: FY2022-23 | B11: Shehbaz Sharif | C11: -0.21 | D11: 29.2 | E11: 62881 | F11: 74.8 | G11: -3.3 | H11: FY23 crisis/flood year. | I11: https://www.finance.gov.pk/publications/DPS_2024.pdf
A12: FY2023-24 | B12: Shehbaz Sharif | C12: 2.38 | D12: 23.4 | E12: 71246 | F12: 67.8 | G12: -2.1 | H12: Debt stock aligned to FY24 debt review / summary series. | I12: https://www.finance.gov.pk/dpco/Annual_Debt_Review_FY24.pdf
A13: FY2024-25 | B13: Shehbaz Sharif | C13: 2.68 | D13: 4.5 | E13: 80518 | F13: 70 | G13: 2.1 | H13: FY25 stabilization year. | I13: https://www.finance.gov.pk/dpco/annual_debt_review_2025.pdf

Sheet Major Loan Programs
A1: Approval / FY | B1: Program / Facility | C1: Lender | D1: Commitment (SDR bn) | E1: Approx. USD bn | F1: Purpose / Where used | G1: Source URL | I1: Total approx. USD bn
A2: Sep 2013 | B2: Extended Fund Facility (EFF) | C2: IMF | D2: 4.393 | E2: 6.7 | F2: Balance-of-payments support; reserves/budget stabilization, fiscal and structural reform. | G2: https://www.imf.org/external/pubs/ft/scr/2013/cr13287.pdf | I2: =SUM(E2:E7)
A3: Jul 2019 | B3: Extended Fund Facility (EFF) | C3: IMF | D3: 4.268 | E3: 6 | F3: Budgetary resource / macro stabilization under reform program. | G3: https://www.imf.org/en/news/articles/2021/03/24/pr2183-pakistan-imf-executive-board-completes-the-combined-2nd-3rd-4th-5th-reviews-of-the-eff
A4: Jul 2023 | B4: Stand-By Arrangement (SBA) | C4: IMF | D4: 2.25 | E4: 3 | F4: Emergency stabilization / near-default avoidance / external financing gap. | G4: https://www.imf.org/en/countries/pak/faq
A5: Sep 2024 | B5: Extended Fund Facility (EFF) | C5: IMF | D5: 5.32 | E5: 7 | F5: Medium-term stabilization, tax/energy reforms, reserve support. | G5: https://www.imf.org/en/countries/pak/faq
A6: May 2025 | B6: Resilience and Sustainability Facility (RSF) | C6: IMF | D6: 1 | E6: 1.4 | F6: Climate and resilience reforms alongside the EFF. | G6: https://www.imf.org/en/news/articles/2025/05/09/pr-25137-pakistan-imf-completes-1st-rev-of-eff-arrang-and-approves-req-for-arrang-under-rsf
A7: Jun 2025 | B7: Islamic finance facility for circular debt | C7: 18 local commercial banks | E7: 4.5 | F7: Used to address power-sector circular debt; repayable over 6 years, quarterly installments. | G7: https://www.reuters.com/sustainability/boards-policy-regulation/pakistan-signs-45-billion-loans-with-local-banks-ease-power-sector-debt-2025-06-20/

Sheet External Flows
A1: FY | B1: Source Type / Creditor | C1: Inflows / Disbursements (USD mn) | D1: Repayments (USD mn) | E1: Interest (USD mn) | F1: Notes | G1: Source URL | I1: FY22 total inflows
A2: FY2016-17 | B2: ADB | C2: 1495 | F2: Official creditor-wise disbursement detail. | G2: https://www.finance.gov.pk/publications/DPS_2017_18.pdf | I2: =SUM(C13:C16)
A3: FY2016-17 | B3: IDA | C3: 665 | F3: Official creditor-wise disbursement detail. | G3: https://www.finance.gov.pk/publications/DPS_2017_18.pdf
A4: FY2016-17 | B4: IsDB | C4: 618 | F4: Official creditor-wise disbursement detail. | G4: https://www.finance.gov.pk/publications/DPS_2017_18.pdf | I4: FY22 total servicing
A5: FY2016-17 | B5: IBRD | C5: 239 | F5: Official creditor-wise disbursement detail. | G5: https://www.finance.gov.pk/publications/DPS_2017_18.pdf | I5: =SUM(D13:D16)+SUM(E13:E16)
A6: FY2016-17 | B6: IMF | C6: 102 | F6: Official creditor-wise disbursement detail. | G6: https://www.finance.gov.pk/publications/DPS_2017_18.pdf
A7: FY2016-17 | B7: China (bilateral) | C7: 1655 | F7: Official creditor-wise disbursement detail. | G7: https://www.finance.gov.pk/publications/DPS_2017_18.pdf | I7: FY23 total inflows
A8: FY2016-17 | B8: France (bilateral) | C8: 119 | F8: Official creditor-wise disbursement detail. | G8: https://www.finance.gov.pk/publications/DPS_2017_18.pdf | I8: =SUM(C17:C20)
A9: FY2016-17 | B9: Saudi Arabia (bilateral) | C9: 69 | F9: Official creditor-wise disbursement detail. | G9: https://www.finance.gov.pk/publications/DPS_2017_18.pdf
A10: FY2016-17 | B10: Japan (bilateral) | C10: 53 | F10: Official creditor-wise disbursement detail. | G10: https://www.finance.gov.pk/publications/DPS_2017_18.pdf | I10: FY23 total servicing
A11: FY2016-17 | B11: Pakistan International Sukuk | C11: 1000 | F11: Official creditor-wise disbursement detail. | G11: https://www.finance.gov.pk/publications/DPS_2017_18.pdf | I11: =SUM(D17:D20)+SUM(E17:E20)
A12: FY2016-17 | B12: Commercial banks total | C12: 4370 | F12: China Development Bank, SCB London, Suisse AG/UBL/ABL, Noor Bank, ICBC, Bank of China, Citibank. | G12: https://www.finance.gov.pk/publications/DPS_2017_18.pdf
A13: FY2021-22 | B13: Multilateral | C13: 5794 | D13: 3201 | E13: 614 | F13: FY22 external inflows and servicing from DPS Jan 2024. | G13: https://www.finance.gov.pk/publications/DPS_2024.pdf
A14: FY2021-22 | B14: Bilateral | C14: 3597 | D14: 1004 | E14: 358 | F14: FY22 external inflows and servicing from DPS Jan 2024. | G14: https://www.finance.gov.pk/publications/DPS_2024.pdf
A15: FY2021-22 | B15: Bonds | C15: 2000 | D15: 1000 | E15: 587 | F15: FY22 external inflows and servicing from DPS Jan 2024. | G15: https://www.finance.gov.pk/publications/DPS_2024.pdf
A16: FY2021-22 | B16: Commercial / Other | C16: 4863 | D16: 5797 | E16: 430 | F16: FY22 external inflows and servicing from DPS Jan 2024. | G16: https://www.finance.gov.pk/publications/DPS_2024.pdf
A17: FY2022-23 | B17: Multilateral | C17: 6309 | D17: 3995 | E17: 1209 | F17: ADB 2.3bn, World Bank 2.0bn, IMF 1.2bn per note. | G17: https://www.finance.gov.pk/publications/DPS_2024.pdf
A18: FY2022-23 | B18: Bilateral | C18: 1380 | D18: 2689 | E18: 772 | F18: ~1.2bn attributed to Saudi Oil Facility. | G18: https://www.finance.gov.pk/publications/DPS_2024.pdf
A19: FY2022-23 | B19: Bonds | C19: 0 | D19: 1000 | E19: 611 | F19: No FY23 new bond inflow in source table. | G19: https://www.finance.gov.pk/publications/DPS_2024.pdf
A20: FY2022-23 | B20: Commercial / Other | C20: 2200 | D20: 7047 | E20: 497 | F20: FY23 commercial/other servicing remained heavy. | G20: https://www.finance.gov.pk/publications/DPS_2024.pdf
A21: FY2024-25 | B21: Multilateral + Commercial (qualitative) | F21: MoF says most inflows came from multilateral and commercial sources; bilateral saw slight net retirement. | G21: https://www.finance.gov.pk/dpco/annual_debt_review_2025.pdf

Sheet Debt Servicing
A1: FY | B1: Metric | C1: Amount | D1: Units | E1: Notes | F1: Source URL
A2: FY2016-17 | B2: External public debt servicing | C2: 6440 | D2: USD mn | E2: MoF says servicing rose 48% YoY. | F2: https://www.finance.gov.pk/publications/DPS_2017_18.pdf
A3: FY2021-22 | B3: Total repayments | C3: 11002 | D3: USD mn | E3: External repayments from DPS Jan 2024 table. | F3: https://www.finance.gov.pk/publications/DPS_2024.pdf
A4: FY2021-22 | B4: Interest payments | C4: 1988 | D4: USD mn | E4: External interest from DPS Jan 2024 table. | F4: https://www.finance.gov.pk/publications/DPS_2024.pdf
A5: FY2021-22 | B5: Total debt servicing | C5: 12990 | D5: USD mn | E5: Repayments + interest. | F5: https://www.finance.gov.pk/publications/DPS_2024.pdf
A6: FY2022-23 | B6: Total repayments | C6: 14732 | D6: USD mn | E6: External repayments from DPS Jan 2024 table. | F6: https://www.finance.gov.pk/publications/DPS_2024.pdf
A7: FY2022-23 | B7: Interest payments | C7: 3088 | D7: USD mn | E7: External interest from DPS Jan 2024 table. | F7: https://www.finance.gov.pk/publications/DPS_2024.pdf
A8: FY2022-23 | B8: Total debt servicing | C8: 17820 | D8: USD mn | E8: Repayments + interest. | F8: https://www.finance.gov.pk/publications/DPS_2024.pdf
A9: FY2024-25 | B9: Federal interest expense | C9: 8887 | D9: PKR bn | E9: Annual Debt Review FY2025. | F9: https://www.finance.gov.pk/dpco/annual_debt_review_2025.pdf
A10: FY2024-25 | B10: Federal fiscal deficit | C10: 7089 | D10: PKR bn | E10: Annual Debt Review FY2025. | F10: https://www.finance.gov.pk/dpco/annual_debt_review_2025.pdf

Sheet Tenure Summary
A1: Tenure | B1: Avg GDP Growth (%) | C1: Avg Inflation (%) | D1: Debt Increase (PKR bn) | E1: Start FY | F1: End FY | G1: Comment | I1: Best growth
A2: Nawaz / PML-N | B2: =AVERAGE('Yearly Macro'!C2:C6) | C2: =AVERAGE('Yearly Macro'!D2:D6) | D2: ='Yearly Macro'!E6-'Yearly Macro'!E2 | E2: FY2013-14 | F2: FY2017-18 | G2: Strongest growth period; external vulnerabilities built up by end. | I2: =INDEX(A2:A4,MATCH(MAX(B2:B4),B2:B4,0))
A3: Imran Khan | B3: =AVERAGE('Yearly Macro'!C7:C10) | C3: =AVERAGE('Yearly Macro'!D7:D10) | D3: ='Yearly Macro'!E10-'Yearly Macro'!E7 | E3: FY2018-19 | F3: FY2021-22 | G3: Growth was volatile: slowdown, COVID contraction, rebound.
A4: Shehbaz Sharif | B4: =AVERAGE('Yearly Macro'!C11:C13) | C4: =AVERAGE('Yearly Macro'!D11:D13) | D4: ='Yearly Macro'!E13-'Yearly Macro'!E11 | E4: FY2022-23 | F4: FY2024-25 | G4: Stabilization improved by FY25, but debt kept climbing. | I4: Largest debt increase
I5: =INDEX(A2:A4,MATCH(MAX(D2:D4),D2:D4,0))

Sheet Provincial Debt
A1: Province | B1: Latest verified snapshot | C1: Debt / Change | D1: Servicing / Risk metric | E1: Where loans are going / notes | F1: Source URL
A2: Punjab | B2: June 2025 debt bulletin | C2: PKR 1,757.2 bn debt stock | D2: FY2024-25 servicing PKR 156.4 bn | E2: Mostly provincial debt portfolio; bulletins separate domestic/external debt and commodity operations influence older years. | F2: https://finance.punjab.gov.pk/details/debt-bulletins
A3: Sindh | B3: June 2025 debt bulletin | C3: FY2024-25 debt increase PKR 284.951 bn | D3: FY2024-25 debt servicing PKR 71.38 bn | E3: Project-linked external loans incl. Karachi, education, health, water, waste, roads, agriculture; lenders include IDA/IBRD, ADB, AFD, IsDB, AIIB. | F3: https://finance.gos.pk/Home/Download?path=SpecializedUnits%2FDMU%2FDEBT+BULLETIN+30-06-25.pdf
A4: Khyber Pakhtunkhwa | B4: FY2024-25 fiscal risk statement | C4: Outstanding debt = 51.9% of total revenue | D4: Debt servicing = 4.1% of total revenue | E4: Risk reporting is ratio-based in available official snippet rather than one headline stock figure. | F4: https://www.pakp.gov.pk/wp-content/uploads/2025/06/dd-KP-Fiscal-Risk-Statement-FY2024-25.pdf
A5: Balochistan | B5: 2025-26 annual budget statement / debt policy | C5: Movement schedule of debt balances by development partner disclosed | D5: Headline stock not surfaced cleanly in search snippet | E5: Official docs show debt scheduling and a foreign debt management policy; use province's finance site for latest table extraction. | F5: https://www.finance.gob.pk/wp-content/uploads/2025/07/ABS-2025-26.pdf

Sheet Charts

Sheet Nawaz
A1: Nawaz political tenure sheet
A2: Covers FY2013-14 through FY2017-18. This groups Nawaz Sharif / PML-N-era fiscal years for political comparison.
A4: Fiscal Year | B4: Real GDP Growth (%) | C4: Inflation (%) | D4: Public Debt (PKR bn) | E4: Debt/GDP (%) | F4: Current Account (USD bn) | G4: Data note | H4: Source URL | J4: KPI | K4: Value
A5: FY2013-14 | B5: ='Yearly Macro'!C2 | C5: ='Yearly Macro'!D2 | D5: ='Yearly Macro'!E2 | E5: ='Yearly Macro'!F2 | F5: ='Yearly Macro'!G2 | G5: Growth & inflation from official year books/surveys; debt from MoF debt statement surfaced in official debt docs. | H5: https://www.finance.gov.pk/publications/YearBook2013_14.pdf | J5: Average GDP Growth (%) | K5: =AVERAGE(B5:B9)
A6: FY2014-15 | B6: ='Yearly Macro'!C3 | C6: ='Yearly Macro'!D3 | D6: ='Yearly Macro'!E3 | E6: ='Yearly Macro'!F3 | F6: ='Yearly Macro'!G3 | G6: Current-account figure shown for Jul-Apr in survey highlights; use with care. | H6: https://www.finance.gov.pk/publications/YearBook2014_15.pdf | J6: Average Inflation (%) | K6: =AVERAGE(C5:C9)
A7: FY2015-16 | B7: ='Yearly Macro'!C4 | C7: ='Yearly Macro'!D4 | D7: ='Yearly Macro'!E4 | E7: ='Yearly Macro'!F4 | F7: ='Yearly Macro'!G4 | G7: Debt row compiled to maintain annual continuity; validate vs SBP summary for publication. | H7: https://www.finance.gov.pk/survey/chapters_16/highlights_2015_16.pdf | J7: Debt Increase (PKR bn) | K7: =D9-D5
A8: FY2016-17 | B8: ='Yearly Macro'!C5 | C8: ='Yearly Macro'!D5 | D8: ='Yearly Macro'!E5 | E8: ='Yearly Macro'!F5 | F8: ='Yearly Macro'!G5 | G8: Official debt stock and GDP ratio from Debt Policy Statement 2017-18. | H8: https://www.finance.gov.pk/publications/DPS_2017_18.pdf | J8: Start Debt/GDP (%) | K8: =E5
A9: FY2017-18 | B9: ='Yearly Macro'!C6 | C9: ='Yearly Macro'!D6 | D9: ='Yearly Macro'!E6 | E9: ='Yearly Macro'!F6 | F9: ='Yearly Macro'!G6 | G9: Debt ratio from DPS 2018-19; debt stock compiled for annual continuity. | H9: https://www.finance.gov.pk/publications/DPS_2018_19.pdf | J9: End Debt/GDP (%) | K9: =E9
J10: Years covered | K10: =ROWS(A5:A9)

Sheet Imran
A1: Imran political tenure sheet
A2: Covers FY2018-19 through FY2021-22. FY2021-22 is assigned to Imran Khan for majority-of-fiscal-year comparability.
A4: Fiscal Year | B4: Real GDP Growth (%) | C4: Inflation (%) | D4: Public Debt (PKR bn) | E4: Debt/GDP (%) | F4: Current Account (USD bn) | G4: Data note | H4: Source URL | J4: KPI | K4: Value
A5: FY2018-19 | B5: ='Yearly Macro'!C7 | C5: ='Yearly Macro'!D7 | D5: ='Yearly Macro'!E7 | E5: ='Yearly Macro'!F7 | F5: ='Yearly Macro'!G7 | G5: Debt stock compiled; debt ratio from official DPS 2019-20 context. | H5: https://www.finance.gov.pk/publications/DPS_2019_2020.pdf | J5: Average GDP Growth (%) | K5: =AVERAGE(B5:B8)
A6: FY2019-20 | B6: ='Yearly Macro'!C8 | C6: ='Yearly Macro'!D8 | D6: ='Yearly Macro'!E8 | E6: ='Yearly Macro'!F8 | F6: ='Yearly Macro'!G8 | G6: COVID year; growth from Economic Survey 2020-21 back-series. | H6: https://www.finance.gov.pk/survey/chapters_21/01-Growth.pdf | J6: Average Inflation (%) | K6: =AVERAGE(C5:C8)
A7: FY2020-21 | B7: ='Yearly Macro'!C9 | C7: ='Yearly Macro'!D9 | D7: ='Yearly Macro'!E9 | E7: ='Yearly Macro'!F9 | F7: ='Yearly Macro'!G9 | G7: Growth from Economic Survey 2020-21; debt series compiled from debt reviews. | H7: https://www.finance.gov.pk/survey/chapters_21/01-Growth.pdf | J7: Debt Increase (PKR bn) | K7: =D8-D5
A8: FY2021-22 | B8: ='Yearly Macro'!C10 | C8: ='Yearly Macro'!D10 | D8: ='Yearly Macro'!E10 | E8: ='Yearly Macro'!F10 | F8: ='Yearly Macro'!G10 | G8: Official debt row surfaced in Debt Policy Statement January 2024 / 2023 review. | H8: https://www.finance.gov.pk/publications/DPS_2023.pdf | J8: Start Debt/GDP (%) | K8: =E5
J9: End Debt/GDP (%) | K9: =E8
J10: Years covered | K10: =ROWS(A5:A8)

Sheet Shehbaz
A1: Shehbaz political tenure sheet
A2: Covers FY2022-23 through FY2024-25. This is the stabilization-focused post-crisis period.
A4: Fiscal Year | B4: Real GDP Growth (%) | C4: Inflation (%) | D4: Public Debt (PKR bn) | E4: Debt/GDP (%) | F4: Current Account (USD bn) | G4: Data note | H4: Source URL | J4: KPI | K4: Value
A5: FY2022-23 | B5: ='Yearly Macro'!C11 | C5: ='Yearly Macro'!D11 | D5: ='Yearly Macro'!E11 | E5: ='Yearly Macro'!F11 | F5: ='Yearly Macro'!G11 | G5: FY23 crisis/flood year. | H5: https://www.finance.gov.pk/publications/DPS_2024.pdf | J5: Average GDP Growth (%) | K5: =AVERAGE(B5:B7)
A6: FY2023-24 | B6: ='Yearly Macro'!C12 | C6: ='Yearly Macro'!D12 | D6: ='Yearly Macro'!E12 | E6: ='Yearly Macro'!F12 | F6: ='Yearly Macro'!G12 | G6: Debt stock aligned to FY24 debt review / summary series. | H6: https://www.finance.gov.pk/dpco/Annual_Debt_Review_FY24.pdf | J6: Average Inflation (%) | K6: =AVERAGE(C5:C7)
A7: FY2024-25 | B7: ='Yearly Macro'!C13 | C7: ='Yearly Macro'!D13 | D7: ='Yearly Macro'!E13 | E7: ='Yearly Macro'!F13 | F7: ='Yearly Macro'!G13 | G7: FY25 stabilization year. | H7: https://www.finance.gov.pk/dpco/annual_debt_review_2025.pdf | J7: Debt Increase (PKR bn) | K7: =D7-D5
J8: Start Debt/GDP (%) | K8: =E5
J9: End Debt/GDP (%) | K9: =E7
J10: Years covered | K10: =ROWS(A5:A7)
